nepalpy/__init__.py
nepalpy/geographical/__init__.py
nepalpy/geographical/districts.py
nepalpy/geographical/mappings.py
nepalpy/geographical/provinces.py
nepalpy/geographical/randomizer.py
nepalpy/name/__init__.py
nepalpy/name/cast.py
nepalpy/name/female_names.py
nepalpy/name/male_names.py
nepalpy/name/name_generator.py
nepalpy-1.3.2.dist-info/licenses/LICENSE
nepalpy-1.3.2.dist-info/METADATA
nepalpy-1.3.2.dist-info/WHEEL
nepalpy-1.3.2.dist-info/top_level.txt
nepalpy-1.3.2.dist-info/RECORD
